{
  "entries": [
    {
      "text": "波紋管可以加速冶煉過程。",
      "rarity": 1.0
    },
    {
      "text": "樓梯上可以鋪地毯。",
      "rarity": 1.0
    },
    {
      "text": "藥水可以在普通的大鍋中混合。",
      "rarity": 1.0
    },
    {
      "text": "在設施齊全的房間裡睡覺可以提升你的屬性。",
      "rarity": 1.0
    },
    {
      "text": "貓頭鷹可用於向其他玩家或倉庫傳遞訊息和包裹。",
      "rarity": 1.0
    },
    {
      "text": "板甲可以很好地保護你免受許多危險。",
      "rarity": 1.0
    },
    {
      "text": "太陽從東方升起，從西方落下。",
      "rarity": 1.0
    },
    {
      "text": "北方天氣越來越冷。",
      "rarity": 1.0
    },
    {
      "text": "有了飼料，動物就會在適當的季節自動繁殖。",
      "rarity": 1.0
    },
    {
      "text": "穿著較重的盔甲會降低躲避攻擊的難度。",
      "rarity": 1.0
    },
    {
      "text": "紙可以用甘蔗或樹皮製成。",
      "rarity": 1.0
    },
    {
      "text": "你可以按「X」來爬行。",
      "rarity": 1.0
    },
    {
      "text": "您可以坐在樓梯和平板上。",
      "rarity": 1.0
    },
    {
      "text": "您一次最多可以攜帶兩袋。",
      "rarity": 1.0
    },
    {
      "text": "驢子、騾子、嗅探者和大象可以攜帶箱子。",
      "rarity": 1.0
    },
    {
      "text": "騎槍和軍刀在馬背上造成更多傷害。",
      "rarity": 1.0
    },
    {
      "text": "直線行駛是非常不切實際的。嘗試獲得有利位置並進行徹底探索。",
      "rarity": 1.0
    },
    {
      "text": "您可以隱藏在樹葉中並安全地降落在樹葉上。",
      "rarity": 1.0
    },
    {
      "text": "掉入淺水中可能會殺死你。",
      "rarity": 1.0
    },
    {
      "text": "北極熊可以用鱈魚馴服。也可以騎乘。",
      "rarity": 1.0
    },
    {
      "text": "帝國衛士的弱點是暴露的背部。",
      "rarity": 1.0
    },
    {
      "text": "屍體在三天後分解。戰利品不會消失。",
      "rarity": 1.0
    },
    {
      "text": "28天後一個季節就過去了。",
      "rarity": 1.0
    },
    {
      "text": "地圖集可以用比例地圖製作。它將使用更少的地圖並繪製出更大的區域。",
      "rarity": 1.0
    },
    {
      "text": "黑鋼可以在北部找到。",
      "rarity": 1.0
    },
    {
      "text": "生存主義者筆記包含許多有用的技巧。",
      "rarity": 1.0
    }
  ]
}